code_combiner/__init__.py
code_combiner/main.py
code_combiner_rag-0.1.2.dist-info/LICENSE
code_combiner_rag-0.1.2.dist-info/METADATA
code_combiner_rag-0.1.2.dist-info/WHEEL
code_combiner_rag-0.1.2.dist-info/entry_points.txt
code_combiner_rag-0.1.2.dist-info/top_level.txt
code_combiner_rag-0.1.2.dist-info/RECORD
