Metadata-Version: 2.2
Name: code-combiner-rag
Version: 0.1.2
Summary: A tool to combine code files into a single file for RAG pipelines
Home-page: https://github.com/bazinga012/code-combiner-rag
Author: Vishal Agrawal
Author-email: vishal18593@gmail.com
Project-URL: Bug Tracker, https://github.com/bazinga012/code-combiner-rag/issues
Keywords: code,combine,rag,llm,ai,machine learning,code-embedding
Classifier: Programming Language :: Python :: 3
Classifier: Programming Language :: Python :: 3.10
Classifier: Programming Language :: Python :: 3.11
Classifier: Programming Language :: Python :: 3.12
Classifier: License :: OSI Approved :: MIT License
Classifier: Operating System :: OS Independent
Classifier: Development Status :: 4 - Beta
Classifier: Intended Audience :: Developers
Classifier: Topic :: Software Development :: Libraries :: Python Modules
Classifier: Topic :: Software Development :: Code Generators
Requires-Python: >=3.10
License-File: LICENSE
Requires-Dist: pyyaml>=5.1
Dynamic: author
Dynamic: author-email
Dynamic: classifier
Dynamic: description
Dynamic: description-content-type
Dynamic: home-page
Dynamic: keywords
Dynamic: project-url
Dynamic: requires-dist
Dynamic: requires-python
Dynamic: summary
